Metadata-Version: 2.1
Name: mptrfhandler
Version: 0.0.7
Summary: 支持按时间滚动的Python多进程日志Handler
Home-page: UNKNOWN
Author: ruan.lj@foxmail.com
Author-email: ruan.lj@foxmail.com
License: UNKNOWN
Project-URL: Source, https://github.com/ruanima/mptrfhandler
Platform: UNKNOWN
Classifier: Development Status :: 4 - Beta
Classifier: Intended Audience :: Developers
Classifier: Topic :: Software Development :: Libraries
Classifier: Programming Language :: Python :: 3
